{"config": {"view": {"continuousWidth": 300, "continuousHeight": 300}, "locale": {"number": {"decimal": ",", "thousands": ".", "grouping": [3], "currency": ["", "\u00a0\u20ac"]}}, "title": {"dx": 30, "dy": -15, "fontSize": 15}}, "data": {"name": "data-c2bb4cce8baad73946dfd1639a0d4b7b"}, "facet": {"column": {"field": "seg2", "header": {"labelFontSize": 15}, "sort": {"field": "order"}, "title": null, "type": "nominal"}, "row": {"field": "row", "header": {"labels": false}, "sort": {"field": "order"}, "title": null, "type": "nominal"}}, "spec": {"layer": [{"mark": {"type": "rule"}, "encoding": {"y": {"aggregate": "mean", "field": "zero", "type": "quantitative"}}, "transform": [{"calculate": "0", "as": "zero"}]}, {"mark": {"type": "errorbar", "ticks": true}, "encoding": {"color": {"field": "seg1", "legend": {"labelFontSize": 12, "symbolSize": 400}, "sort": {"field": "order"}, "title": null, "type": "nominal"}, "tooltip": {"value": null}, "x": {"axis": {"labelAngle": 0, "labelFontSize": 11}, "field": "M", "sort": {"field": "order"}, "title": null, "type": "nominal"}, "y": {"axis": {"format": "%", "labelFontSize": 11}, "field": "lower", "title": null, "type": "quantitative"}, "y2": {"field": "upper"}}}, {"mark": {"type": "line", "point": {"size": 50}}, "encoding": {"color": {"field": "seg1", "legend": {"labelFontSize": 12, "symbolSize": 400}, "sort": {"field": "order"}, "title": null, "type": "nominal"}, "tooltip": [{"field": "seg1", "title": "Grupo", "type": "nominal"}, {"field": "prop", "format": ".2%", "title": "Raz\u00f3n", "type": "quantitative"}, {"field": "lower", "format": ".2%", "title": "L\u00edmite inferior", "type": "quantitative"}, {"field": "upper", "format": ".2%", "title": "L\u00edmite superior", "type": "quantitative"}], "x": {"axis": {"labelAngle": 0, "labelFontSize": 11}, "field": "M", "sort": {"field": "order"}, "title": null, "type": "nominal"}, "y": {"axis": {"format": "%", "labelFontSize": 11}, "field": "prop", "title": null, "type": "quantitative"}}, "name": "view_418"}], "height": 175, "width": 175}, "params": [{"name": "param_931", "select": {"type": "interval", "encodings": ["x", "y"]}, "bind": "scales", "views": ["view_418"]}], "resolve": {"axis": {"x": "independent", "y": "independent"}}, "title": {"text": ["Raz\u00f3n de empeoramiento ((empeora - mejora) / mejora) de: Tengo la posibilidad de hablar con alguien de mis problemas personales y familiares", "que empeora de una medici\u00f3n a la previa, seg\u00fan sexo y grado de urbanizaci\u00f3n (porcentajes e intervalos de confianza al 95%)"], "subtitle": "Fuente: Encuesta Sanitaria y Social de Andaluc\u00eda. C\u00f3digo de variable: P23_7"}, "transform": [{"calculate": "datum.seg1 == 'Total'", "as": "row"}, {"filter": "indexof(datum.M, 'M') != -1"}], "$schema": "https://vega.github.io/schema/vega-lite/v5.14.1.json", "datasets": {"data-c2bb4cce8baad73946dfd1639a0d4b7b": [{"M": "M3-M2", "seg1": "Hombre", "seg2": "Urbano", "prop": -0.2997339080877119, "lower": -0.5139921875173002, "upper": -0.023700248376370355, "order": 0}, {"M": "M3-M2", "seg1": "Hombre", "seg2": "Intermedio", "prop": 0.21660762429759883, "lower": -0.19706683951172418, "upper": 0.7563850334689135, "order": 1}, {"M": "M3-M2", "seg1": "Hombre", "seg2": "Rural", "prop": -0.11407523618700066, "lower": -0.5676857008454478, "upper": 0.9592638481942358, "order": 2}, {"M": "M3-M2", "seg1": "Hombre", "seg2": "Total", "prop": -0.1025645950469457, "lower": -0.31519888793967005, "upper": 0.180752073417145, "order": 3}, {"M": "M3-M2", "seg1": "Mujer", "seg2": "Urbano", "prop": -0.028767457964332846, "lower": -0.25780123132558563, "upper": 0.31658802264818814, "order": 4}, {"M": "M3-M2", "seg1": "Mujer", "seg2": "Intermedio", "prop": -0.24192544974589347, "lower": -0.4567263501764755, "upper": 0.03123530859064238, "order": 5}, {"M": "M3-M2", "seg1": "Mujer", "seg2": "Rural", "prop": -0.3790325175535164, "lower": -0.7061013065822275, "upper": 0.11287353702666075, "order": 6}, {"M": "M3-M2", "seg1": "Mujer", "seg2": "Total", "prop": -0.16795113805027256, "lower": -0.32432409990041894, "upper": 0.03213862792457907, "order": 7}, {"M": "M3-M2", "seg1": "Total", "seg2": "Urbano", "prop": -0.1742791150720909, "lower": -0.3569160465284739, "upper": 0.0390032019546815, "order": 8}, {"M": "M3-M2", "seg1": "Total", "seg2": "Intermedio", "prop": -0.05117532573870561, "lower": -0.26250253887269975, "upper": 0.22816452979689894, "order": 9}, {"M": "M3-M2", "seg1": "Total", "seg2": "Rural", "prop": -0.2419581737584632, "lower": -0.5400479965919955, "upper": 0.36517097476244986, "order": 10}, {"M": "M3-M2", "seg1": "Total", "seg2": "Total", "prop": -0.13606933853391245, "lower": -0.27798039993594403, "upper": 0.020707410929027115, "order": 11}, {"M": "M4-M3", "seg1": "Hombre", "seg2": "Urbano", "prop": 0.29068029806570816, "lower": -0.10552027099616947, "upper": 0.9797820412165179, "order": 12}, {"M": "M4-M3", "seg1": "Hombre", "seg2": "Intermedio", "prop": -0.25330645845758504, "lower": -0.4988354153271846, "upper": 0.04741921237684322, "order": 13}, {"M": "M4-M3", "seg1": "Hombre", "seg2": "Rural", "prop": 0.3840621172311067, "lower": -0.3539923439398587, "upper": 1.7321336245506742, "order": 14}, {"M": "M4-M3", "seg1": "Hombre", "seg2": "Total", "prop": 0.047142920969030555, "lower": -0.18129670088675287, "upper": 0.38605547071176, "order": 15}, {"M": "M4-M3", "seg1": "Mujer", "seg2": "Urbano", "prop": 0.38542124129700017, "lower": 0.06407984207730576, "upper": 0.795686592077163, "order": 16}, {"M": "M4-M3", "seg1": "Mujer", "seg2": "Intermedio", "prop": 0.29727148232937367, "lower": -0.04701529103911955, "upper": 0.7713804249487262, "order": 17}, {"M": "M4-M3", "seg1": "Mujer", "seg2": "Rural", "prop": 0.36792186014079065, "lower": -0.2903622333811447, "upper": 1.7641442950434536, "order": 18}, {"M": "M4-M3", "seg1": "Mujer", "seg2": "Total", "prop": 0.3503731707359114, "lower": 0.119268066648134, "upper": 0.6286666825774726, "order": 19}, {"M": "M4-M3", "seg1": "Total", "seg2": "Urbano", "prop": 0.34042155533460894, "lower": 0.08224116656769144, "upper": 0.7050161723153602, "order": 20}, {"M": "M4-M3", "seg1": "Total", "seg2": "Intermedio", "prop": -0.02796993497869239, "lower": -0.24659925806047608, "upper": 0.24600614617378797, "order": 21}, {"M": "M4-M3", "seg1": "Total", "seg2": "Rural", "prop": 0.37733783115175096, "lower": -0.20882086683233314, "upper": 1.2892667331906966, "order": 22}, {"M": "M4-M3", "seg1": "Total", "seg2": "Total", "prop": 0.18757144442293086, "lower": 0.0036081438394838885, "upper": 0.3920455288779539, "order": 23}]}}