{"config": {"view": {"continuousWidth": 300, "continuousHeight": 300, "strokeWidth": 0}, "locale": {"number": {"decimal": ",", "thousands": ".", "grouping": [3], "currency": ["", "\u00a0\u20ac"]}}, "title": {"dx": 60, "dy": -15, "fontSize": 15}}, "data": {"name": "data-d77b25518df568ba070533d5f028539d"}, "facet": {"column": {"field": "seg2", "header": {"labelFontSize": 15}, "sort": {"field": "order"}, "title": null, "type": "nominal"}, "row": {"field": "seg1", "header": {"labelFontSize": 15}, "sort": {"field": "order"}, "title": null, "type": "nominal"}}, "spec": {"layer": [{"mark": {"type": "bar"}, "encoding": {"color": {"field": "cat", "legend": {"labelFontSize": 12, "labelLimit": 0, "symbolSize": 400}, "scale": {"domain": ["S\u00ed", "No"], "reverse": true, "scheme": "spectral"}, "title": null, "type": "nominal"}, "tooltip": [{"field": "cat", "title": "Valor", "type": "nominal"}, {"field": "prop", "format": ".2%", "title": "Estimaci\u00f3n", "type": "quantitative"}, {"field": "lower", "format": ".2%", "title": "L\u00edmite inferior", "type": "quantitative"}, {"field": "upper", "format": ".2%", "title": "L\u00edmite superior", "type": "quantitative"}], "y": {"axis": {"format": "%", "labelFontSize": 11}, "field": "prop", "scale": {"nice": false}, "title": null, "type": "quantitative"}}, "name": "view_3246"}, {"mark": {"type": "errorbar", "color": "black", "ticks": {"width": 10}}, "encoding": {"opacity": {"condition": {"test": "(datum.n_cat === 1)", "value": 1}, "value": 0}, "tooltip": {"value": null}, "y": {"axis": {"format": "%", "labelFontSize": 11}, "field": "lower", "scale": {"nice": false}, "title": null, "type": "quantitative"}, "y2": {"field": "upper"}}}], "encoding": {"order": {"field": "order", "sort": "descending", "type": "quantitative"}, "x": {"axis": {"labelAngle": 0, "labelFontSize": 11}, "field": "M", "sort": {"field": "order"}, "title": null, "type": "nominal"}}, "height": 175, "width": {"step": 45, "for": "position"}}, "params": [{"name": "param_3954", "select": {"type": "point", "fields": ["cat"], "on": "click", "toggle": "true"}, "bind": "legend", "views": ["view_3246"]}, {"name": "param_3955", "select": {"type": "interval", "encodings": ["x", "y"]}, "bind": "scales", "views": ["view_3246"]}], "resolve": {"axis": {"x": "independent", "y": "independent"}}, "title": {"text": ["Poblaci\u00f3n que con las horas que duerme, descansa lo suficiente por medici\u00f3n,", "sexo y nivel de estudios (porcentajes e intervalos de confianza al 95%)"], "subtitle": "Fuente: Encuesta Sanitaria y Social de Andaluc\u00eda. C\u00f3digo de variable: P37A"}, "transform": [{"filter": {"param": "param_3954"}}, {"joinaggregate": [{"op": "distinct", "field": "cat", "as": "n_cat"}]}, {"filter": "true == true"}], "$schema": "https://vega.github.io/schema/vega-lite/v5.20.1.json", "datasets": {"data-d77b25518df568ba070533d5f028539d": [{"M": "M2", "seg1": "Hombre", "seg2": ["Hasta", "primaria"], "cat": "S\u00ed", "prop": 0.8287707781373232, "lower": 0.7507549838589092, "upper": 0.8935411199083492, "order": 0}, {"M": "M2", "seg1": "Hombre", "seg2": ["Hasta", "primaria"], "cat": "No", "prop": 0.17122922186267678, "lower": 0.10645888009165046, "upper": 0.24924501614109099, "order": 1}, {"M": "M2", "seg1": "Hombre", "seg2": ["Secundaria o", "FP grado sup"], "cat": "S\u00ed", "prop": 0.8195968068078289, "lower": 0.7540906439695767, "upper": 0.8609735083264837, "order": 2}, {"M": "M2", "seg1": "Hombre", "seg2": ["Secundaria o", "FP grado sup"], "cat": "No", "prop": 0.18040319319217119, "lower": 0.13902649167351633, "upper": 0.24590935603042255, "order": 3}, {"M": "M2", "seg1": "Hombre", "seg2": ["Estudios", "universitarios", "o m\u00e1s"], "cat": "S\u00ed", "prop": 0.7655762626727867, "lower": 0.6842928608095898, "upper": 0.8230468738597642, "order": 4}, {"M": "M2", "seg1": "Hombre", "seg2": ["Estudios", "universitarios", "o m\u00e1s"], "cat": "No", "prop": 0.23442373732721322, "lower": 0.17695312614023595, "upper": 0.31570713919041016, "order": 5}, {"M": "M2", "seg1": "Hombre", "seg2": ["Total"], "cat": "S\u00ed", "prop": 0.8012659849608367, "lower": 0.765497112276605, "upper": 0.834802555946085, "order": 6}, {"M": "M2", "seg1": "Hombre", "seg2": ["Total"], "cat": "No", "prop": 0.19873401503916324, "lower": 0.16519744405391473, "upper": 0.23450288772339492, "order": 7}, {"M": "M2", "seg1": "Mujer", "seg2": ["Hasta", "primaria"], "cat": "S\u00ed", "prop": 0.8107811064466365, "lower": 0.7363725105107874, "upper": 0.8633968496467738, "order": 8}, {"M": "M2", "seg1": "Mujer", "seg2": ["Hasta", "primaria"], "cat": "No", "prop": 0.18921889355336363, "lower": 0.13660315035322637, "upper": 0.26362748948921283, "order": 9}, {"M": "M2", "seg1": "Mujer", "seg2": ["Secundaria o", "FP grado sup"], "cat": "S\u00ed", "prop": 0.7341505203390457, "lower": 0.6909058681752648, "upper": 0.7845143177597989, "order": 10}, {"M": "M2", "seg1": "Mujer", "seg2": ["Secundaria o", "FP grado sup"], "cat": "No", "prop": 0.26584947966095424, "lower": 0.2154856822402013, "upper": 0.30909413182473544, "order": 11}, {"M": "M2", "seg1": "Mujer", "seg2": ["Estudios", "universitarios", "o m\u00e1s"], "cat": "S\u00ed", "prop": 0.6968725733404887, "lower": 0.6365070087147209, "upper": 0.7440677059123576, "order": 12}, {"M": "M2", "seg1": "Mujer", "seg2": ["Estudios", "universitarios", "o m\u00e1s"], "cat": "No", "prop": 0.3031274266595116, "lower": 0.2559322940876424, "upper": 0.36349299128527907, "order": 13}, {"M": "M2", "seg1": "Mujer", "seg2": ["Total"], "cat": "S\u00ed", "prop": 0.7356347152905229, "lower": 0.7020838683568242, "upper": 0.7650551518286383, "order": 14}, {"M": "M2", "seg1": "Mujer", "seg2": ["Total"], "cat": "No", "prop": 0.26436528470947707, "lower": 0.23494484817136163, "upper": 0.2979161316431758, "order": 15}, {"M": "M2", "seg1": "Total", "seg2": ["Hasta", "primaria"], "cat": "S\u00ed", "prop": 0.8185841785891687, "lower": 0.7650918734046117, "upper": 0.8643686131938779, "order": 16}, {"M": "M2", "seg1": "Total", "seg2": ["Hasta", "primaria"], "cat": "No", "prop": 0.18141582141083135, "lower": 0.135631386806122, "upper": 0.23490812659538818, "order": 17}, {"M": "M2", "seg1": "Total", "seg2": ["Secundaria o", "FP grado sup"], "cat": "S\u00ed", "prop": 0.7755322683378861, "lower": 0.7425364649775086, "upper": 0.8097741096758684, "order": 18}, {"M": "M2", "seg1": "Total", "seg2": ["Secundaria o", "FP grado sup"], "cat": "No", "prop": 0.22446773166211398, "lower": 0.1902258903241315, "upper": 0.2574635350224914, "order": 19}, {"M": "M2", "seg1": "Total", "seg2": ["Estudios", "universitarios", "o m\u00e1s"], "cat": "S\u00ed", "prop": 0.730301151029251, "lower": 0.682652354292566, "upper": 0.7701700825334548, "order": 20}, {"M": "M2", "seg1": "Total", "seg2": ["Estudios", "universitarios", "o m\u00e1s"], "cat": "No", "prop": 0.2696988489707491, "lower": 0.22982991746654538, "upper": 0.31734764570743407, "order": 21}, {"M": "M2", "seg1": "Total", "seg2": ["Total"], "cat": "S\u00ed", "prop": 0.7668887872292486, "lower": 0.7392645178951968, "upper": 0.788262132423324, "order": 22}, {"M": "M2", "seg1": "Total", "seg2": ["Total"], "cat": "No", "prop": 0.23311121277075134, "lower": 0.2117378675766761, "upper": 0.2607354821048033, "order": 23}, {"M": "M3", "seg1": "Hombre", "seg2": ["Hasta", "primaria"], "cat": "S\u00ed", "prop": 0.8716738002383935, "lower": 0.8154648212765369, "upper": 0.9125270454297153, "order": 24}, {"M": "M3", "seg1": "Hombre", "seg2": ["Hasta", "primaria"], "cat": "No", "prop": 0.12832619976160653, "lower": 0.08747295457028495, "upper": 0.18453517872346364, "order": 25}, {"M": "M3", "seg1": "Hombre", "seg2": ["Secundaria o", "FP grado sup"], "cat": "S\u00ed", "prop": 0.7943866715406916, "lower": 0.7406008293163544, "upper": 0.8275333635062221, "order": 26}, {"M": "M3", "seg1": "Hombre", "seg2": ["Secundaria o", "FP grado sup"], "cat": "No", "prop": 0.20561332845930844, "lower": 0.17246663649377783, "upper": 0.2593991706836455, "order": 27}, {"M": "M3", "seg1": "Hombre", "seg2": ["Estudios", "universitarios", "o m\u00e1s"], "cat": "S\u00ed", "prop": 0.7657253384323476, "lower": 0.7126182609488139, "upper": 0.810981916349406, "order": 28}, {"M": "M3", "seg1": "Hombre", "seg2": ["Estudios", "universitarios", "o m\u00e1s"], "cat": "No", "prop": 0.23427466156765264, "lower": 0.18901808365059433, "upper": 0.2873817390511874, "order": 29}, {"M": "M3", "seg1": "Hombre", "seg2": ["Total"], "cat": "S\u00ed", "prop": 0.8004449428032487, "lower": 0.7694599253842325, "upper": 0.8247528271079242, "order": 30}, {"M": "M3", "seg1": "Hombre", "seg2": ["Total"], "cat": "No", "prop": 0.19955505719675118, "lower": 0.17524717289207584, "upper": 0.23054007461576737, "order": 31}, {"M": "M3", "seg1": "Mujer", "seg2": ["Hasta", "primaria"], "cat": "S\u00ed", "prop": 0.8164194333854563, "lower": 0.7679356736271296, "upper": 0.8603728666618746, "order": 32}, {"M": "M3", "seg1": "Mujer", "seg2": ["Hasta", "primaria"], "cat": "No", "prop": 0.1835805666145438, "lower": 0.1396271333381253, "upper": 0.23206432637287044, "order": 33}, {"M": "M3", "seg1": "Mujer", "seg2": ["Secundaria o", "FP grado sup"], "cat": "S\u00ed", "prop": 0.6857172404391285, "lower": 0.6431638210944537, "upper": 0.7259404446022426, "order": 34}, {"M": "M3", "seg1": "Mujer", "seg2": ["Secundaria o", "FP grado sup"], "cat": "No", "prop": 0.31428275956087154, "lower": 0.27405955539775745, "upper": 0.35683617890554636, "order": 35}, {"M": "M3", "seg1": "Mujer", "seg2": ["Estudios", "universitarios", "o m\u00e1s"], "cat": "S\u00ed", "prop": 0.6637105677384565, "lower": 0.6204994451904918, "upper": 0.7069835722249294, "order": 36}, {"M": "M3", "seg1": "Mujer", "seg2": ["Estudios", "universitarios", "o m\u00e1s"], "cat": "No", "prop": 0.33628943226154345, "lower": 0.29301642777507103, "upper": 0.3795005548095084, "order": 37}, {"M": "M3", "seg1": "Mujer", "seg2": ["Total"], "cat": "S\u00ed", "prop": 0.7081200171556623, "lower": 0.6821157757143959, "upper": 0.7324125986497221, "order": 38}, {"M": "M3", "seg1": "Mujer", "seg2": ["Total"], "cat": "No", "prop": 0.29187998284433775, "lower": 0.2675874013502782, "upper": 0.3178842242856044, "order": 39}, {"M": "M3", "seg1": "Total", "seg2": ["Hasta", "primaria"], "cat": "S\u00ed", "prop": 0.8410847654328152, "lower": 0.8062312181296513, "upper": 0.8687468468617626, "order": 40}, {"M": "M3", "seg1": "Total", "seg2": ["Hasta", "primaria"], "cat": "No", "prop": 0.1589152345671851, "lower": 0.13125315313823735, "upper": 0.19376878187034882, "order": 41}, {"M": "M3", "seg1": "Total", "seg2": ["Secundaria o", "FP grado sup"], "cat": "S\u00ed", "prop": 0.7401809132345294, "lower": 0.7069442679594892, "upper": 0.7689685811277427, "order": 42}, {"M": "M3", "seg1": "Total", "seg2": ["Secundaria o", "FP grado sup"], "cat": "No", "prop": 0.2598190867654708, "lower": 0.23103141887225753, "upper": 0.2930557320405112, "order": 43}, {"M": "M3", "seg1": "Total", "seg2": ["Estudios", "universitarios", "o m\u00e1s"], "cat": "S\u00ed", "prop": 0.711908168478231, "lower": 0.6763255694948337, "upper": 0.7425625364179343, "order": 44}, {"M": "M3", "seg1": "Total", "seg2": ["Estudios", "universitarios", "o m\u00e1s"], "cat": "No", "prop": 0.288091831521769, "lower": 0.25743746358206565, "upper": 0.32367443050516637, "order": 45}, {"M": "M3", "seg1": "Total", "seg2": ["Total"], "cat": "S\u00ed", "prop": 0.7524320620782602, "lower": 0.7338344774551665, "upper": 0.7715431311485998, "order": 46}, {"M": "M3", "seg1": "Total", "seg2": ["Total"], "cat": "No", "prop": 0.24756793792173987, "lower": 0.2284568688514002, "upper": 0.2661655225448335, "order": 47}, {"M": "M4", "seg1": "Hombre", "seg2": ["Hasta", "primaria"], "cat": "S\u00ed", "prop": 0.8879219280314907, "lower": 0.844033620074367, "upper": 0.9238287401535025, "order": 48}, {"M": "M4", "seg1": "Hombre", "seg2": ["Hasta", "primaria"], "cat": "No", "prop": 0.11207807196850925, "lower": 0.07617125984649749, "upper": 0.1559663799256331, "order": 49}, {"M": "M4", "seg1": "Hombre", "seg2": ["Secundaria o", "FP grado sup"], "cat": "S\u00ed", "prop": 0.7797169983286084, "lower": 0.7329425189806063, "upper": 0.8156688128441137, "order": 50}, {"M": "M4", "seg1": "Hombre", "seg2": ["Secundaria o", "FP grado sup"], "cat": "No", "prop": 0.22028300167139162, "lower": 0.1843311871558866, "upper": 0.2670574810193942, "order": 51}, {"M": "M4", "seg1": "Hombre", "seg2": ["Estudios", "universitarios", "o m\u00e1s"], "cat": "S\u00ed", "prop": 0.7867568393298519, "lower": 0.743797771836309, "upper": 0.8260932724386424, "order": 52}, {"M": "M4", "seg1": "Hombre", "seg2": ["Estudios", "universitarios", "o m\u00e1s"], "cat": "No", "prop": 0.2132431606701483, "lower": 0.1739067275613575, "upper": 0.2562022281636908, "order": 53}, {"M": "M4", "seg1": "Hombre", "seg2": ["Total"], "cat": "S\u00ed", "prop": 0.8045512585023605, "lower": 0.7781335798657242, "upper": 0.8269090270721672, "order": 54}, {"M": "M4", "seg1": "Hombre", "seg2": ["Total"], "cat": "No", "prop": 0.19544874149763936, "lower": 0.1730909729278328, "upper": 0.22186642013427563, "order": 55}, {"M": "M4", "seg1": "Mujer", "seg2": ["Hasta", "primaria"], "cat": "S\u00ed", "prop": 0.8099873471146484, "lower": 0.7652429619125813, "upper": 0.8467577073798548, "order": 56}, {"M": "M4", "seg1": "Mujer", "seg2": ["Hasta", "primaria"], "cat": "No", "prop": 0.19001265288535155, "lower": 0.15324229262014516, "upper": 0.2347570380874188, "order": 57}, {"M": "M4", "seg1": "Mujer", "seg2": ["Secundaria o", "FP grado sup"], "cat": "S\u00ed", "prop": 0.688334276364823, "lower": 0.6504769255736222, "upper": 0.7231551275065814, "order": 58}, {"M": "M4", "seg1": "Mujer", "seg2": ["Secundaria o", "FP grado sup"], "cat": "No", "prop": 0.311665723635177, "lower": 0.2768448724934185, "upper": 0.34952307442637787, "order": 59}, {"M": "M4", "seg1": "Mujer", "seg2": ["Estudios", "universitarios", "o m\u00e1s"], "cat": "S\u00ed", "prop": 0.6643866732581725, "lower": 0.6208491506900099, "upper": 0.7018246179376575, "order": 60}, {"M": "M4", "seg1": "Mujer", "seg2": ["Estudios", "universitarios", "o m\u00e1s"], "cat": "No", "prop": 0.33561332674182764, "lower": 0.2981753820623426, "upper": 0.37915084930999027, "order": 61}, {"M": "M4", "seg1": "Mujer", "seg2": ["Total"], "cat": "S\u00ed", "prop": 0.7115816006548822, "lower": 0.6891644147297125, "upper": 0.7323338620821697, "order": 62}, {"M": "M4", "seg1": "Mujer", "seg2": ["Total"], "cat": "No", "prop": 0.2884183993451178, "lower": 0.26766613791783034, "upper": 0.3108355852702876, "order": 63}, {"M": "M4", "seg1": "Total", "seg2": ["Hasta", "primaria"], "cat": "S\u00ed", "prop": 0.8444346515217503, "lower": 0.81117994329209, "upper": 0.8719104742267904, "order": 64}, {"M": "M4", "seg1": "Total", "seg2": ["Hasta", "primaria"], "cat": "No", "prop": 0.15556534847824974, "lower": 0.12808952577320964, "upper": 0.18882005670791002, "order": 65}, {"M": "M4", "seg1": "Total", "seg2": ["Secundaria o", "FP grado sup"], "cat": "S\u00ed", "prop": 0.736131685611257, "lower": 0.7059310015709995, "upper": 0.7581085957124731, "order": 66}, {"M": "M4", "seg1": "Total", "seg2": ["Secundaria o", "FP grado sup"], "cat": "No", "prop": 0.2638683143887431, "lower": 0.24189140428752692, "upper": 0.29406899842900047, "order": 67}, {"M": "M4", "seg1": "Total", "seg2": ["Estudios", "universitarios", "o m\u00e1s"], "cat": "S\u00ed", "prop": 0.7234784723465512, "lower": 0.6946097783523543, "upper": 0.7508456771211641, "order": 68}, {"M": "M4", "seg1": "Total", "seg2": ["Estudios", "universitarios", "o m\u00e1s"], "cat": "No", "prop": 0.27652152765344873, "lower": 0.24915432287883604, "upper": 0.3053902216476459, "order": 69}, {"M": "M4", "seg1": "Total", "seg2": ["Total"], "cat": "S\u00ed", "prop": 0.7572653400698524, "lower": 0.7394149453481302, "upper": 0.7745086011486765, "order": 70}, {"M": "M4", "seg1": "Total", "seg2": ["Total"], "cat": "No", "prop": 0.24273465993014767, "lower": 0.22549139885132344, "upper": 0.2605850546518698, "order": 71}, {"M": "M5", "seg1": "Hombre", "seg2": ["Hasta", "primaria"], "cat": "S\u00ed", "prop": 0.8359557216771208, "lower": 0.7646562745422728, "upper": 0.9022664591380778, "order": 72}, {"M": "M5", "seg1": "Hombre", "seg2": ["Hasta", "primaria"], "cat": "No", "prop": 0.16404427832287907, "lower": 0.09773354086192212, "upper": 0.23534372545772766, "order": 73}, {"M": "M5", "seg1": "Hombre", "seg2": ["Secundaria o", "FP grado sup"], "cat": "S\u00ed", "prop": 0.7489947040719361, "lower": 0.6964593190042391, "upper": 0.8005983008958567, "order": 74}, {"M": "M5", "seg1": "Hombre", "seg2": ["Secundaria o", "FP grado sup"], "cat": "No", "prop": 0.2510052959280638, "lower": 0.19940169910414315, "upper": 0.3035406809957608, "order": 75}, {"M": "M5", "seg1": "Hombre", "seg2": ["Estudios", "universitarios", "o m\u00e1s"], "cat": "S\u00ed", "prop": 0.7268601639560671, "lower": 0.6531340209969344, "upper": 0.7829885628570544, "order": 76}, {"M": "M5", "seg1": "Hombre", "seg2": ["Estudios", "universitarios", "o m\u00e1s"], "cat": "No", "prop": 0.2731398360439329, "lower": 0.21701143714294552, "upper": 0.3468659790030656, "order": 77}, {"M": "M5", "seg1": "Hombre", "seg2": ["Total"], "cat": "S\u00ed", "prop": 0.7578544060560207, "lower": 0.7185560255981746, "upper": 0.7921304472751736, "order": 78}, {"M": "M5", "seg1": "Hombre", "seg2": ["Total"], "cat": "No", "prop": 0.24214559394397944, "lower": 0.20786955272482657, "upper": 0.28144397440182545, "order": 79}, {"M": "M5", "seg1": "Mujer", "seg2": ["Hasta", "primaria"], "cat": "S\u00ed", "prop": 0.7525602825212628, "lower": 0.6664115381052204, "upper": 0.8198102991120436, "order": 80}, {"M": "M5", "seg1": "Mujer", "seg2": ["Hasta", "primaria"], "cat": "No", "prop": 0.24743971747873728, "lower": 0.1801897008879563, "upper": 0.33358846189477986, "order": 81}, {"M": "M5", "seg1": "Mujer", "seg2": ["Secundaria o", "FP grado sup"], "cat": "S\u00ed", "prop": 0.6292325868880454, "lower": 0.5744890492421219, "upper": 0.6791039627644211, "order": 82}, {"M": "M5", "seg1": "Mujer", "seg2": ["Secundaria o", "FP grado sup"], "cat": "No", "prop": 0.37076741311195466, "lower": 0.3208960372355788, "upper": 0.4255109507578781, "order": 83}, {"M": "M5", "seg1": "Mujer", "seg2": ["Estudios", "universitarios", "o m\u00e1s"], "cat": "S\u00ed", "prop": 0.66222669935991, "lower": 0.6109947712805298, "upper": 0.7130682912919469, "order": 84}, {"M": "M5", "seg1": "Mujer", "seg2": ["Estudios", "universitarios", "o m\u00e1s"], "cat": "No", "prop": 0.3377733006400902, "lower": 0.2869317087080532, "upper": 0.3890052287194702, "order": 85}, {"M": "M5", "seg1": "Mujer", "seg2": ["Total"], "cat": "S\u00ed", "prop": 0.6712594727159356, "lower": 0.6368648744189512, "upper": 0.7033028238795271, "order": 86}, {"M": "M5", "seg1": "Mujer", "seg2": ["Total"], "cat": "No", "prop": 0.3287405272840644, "lower": 0.2966971761204727, "upper": 0.3631351255810486, "order": 87}, {"M": "M5", "seg1": "Total", "seg2": ["Hasta", "primaria"], "cat": "S\u00ed", "prop": 0.7864788696379844, "lower": 0.7301963378483849, "upper": 0.8372006548629765, "order": 88}, {"M": "M5", "seg1": "Total", "seg2": ["Hasta", "primaria"], "cat": "No", "prop": 0.21352113036201553, "lower": 0.1627993451370234, "upper": 0.26980366215161494, "order": 89}, {"M": "M5", "seg1": "Total", "seg2": ["Secundaria o", "FP grado sup"], "cat": "S\u00ed", "prop": 0.6891136872380133, "lower": 0.6508308670703545, "upper": 0.7267900861709525, "order": 90}, {"M": "M5", "seg1": "Total", "seg2": ["Secundaria o", "FP grado sup"], "cat": "No", "prop": 0.3108863127619865, "lower": 0.2732099138290477, "upper": 0.3491691329296455, "order": 91}, {"M": "M5", "seg1": "Total", "seg2": ["Estudios", "universitarios", "o m\u00e1s"], "cat": "S\u00ed", "prop": 0.6934272968725373, "lower": 0.6492034857110262, "upper": 0.7273559099822848, "order": 92}, {"M": "M5", "seg1": "Total", "seg2": ["Estudios", "universitarios", "o m\u00e1s"], "cat": "No", "prop": 0.30657270312746254, "lower": 0.27264409001771495, "upper": 0.3507965142889737, "order": 93}, {"M": "M5", "seg1": "Total", "seg2": ["Total"], "cat": "S\u00ed", "prop": 0.7122469234491692, "lower": 0.6887495754540606, "upper": 0.735676549398639, "order": 94}, {"M": "M5", "seg1": "Total", "seg2": ["Total"], "cat": "No", "prop": 0.28775307655083066, "lower": 0.2643234506013609, "upper": 0.31125042454593943, "order": 95}, {"M": "Mz1", "seg1": "Hombre", "seg2": ["Hasta", "primaria"], "cat": "S\u00ed", "prop": null, "lower": null, "upper": null, "order": 96}, {"M": "Mz1", "seg1": "Hombre", "seg2": ["Hasta", "primaria"], "cat": "No", "prop": null, "lower": null, "upper": null, "order": 97}, {"M": "Mz1", "seg1": "Hombre", "seg2": ["Secundaria o", "FP grado sup"], "cat": "S\u00ed", "prop": null, "lower": null, "upper": null, "order": 98}, {"M": "Mz1", "seg1": "Hombre", "seg2": ["Secundaria o", "FP grado sup"], "cat": "No", "prop": null, "lower": null, "upper": null, "order": 99}, {"M": "Mz1", "seg1": "Hombre", "seg2": ["Estudios", "universitarios", "o m\u00e1s"], "cat": "S\u00ed", "prop": null, "lower": null, "upper": null, "order": 100}, {"M": "Mz1", "seg1": "Hombre", "seg2": ["Estudios", "universitarios", "o m\u00e1s"], "cat": "No", "prop": null, "lower": null, "upper": null, "order": 101}, {"M": "Mz1", "seg1": "Hombre", "seg2": ["Total"], "cat": "S\u00ed", "prop": null, "lower": null, "upper": null, "order": 102}, {"M": "Mz1", "seg1": "Hombre", "seg2": ["Total"], "cat": "No", "prop": null, "lower": null, "upper": null, "order": 103}, {"M": "Mz1", "seg1": "Mujer", "seg2": ["Hasta", "primaria"], "cat": "S\u00ed", "prop": null, "lower": null, "upper": null, "order": 104}, {"M": "Mz1", "seg1": "Mujer", "seg2": ["Hasta", "primaria"], "cat": "No", "prop": null, "lower": null, "upper": null, "order": 105}, {"M": "Mz1", "seg1": "Mujer", "seg2": ["Secundaria o", "FP grado sup"], "cat": "S\u00ed", "prop": null, "lower": null, "upper": null, "order": 106}, {"M": "Mz1", "seg1": "Mujer", "seg2": ["Secundaria o", "FP grado sup"], "cat": "No", "prop": null, "lower": null, "upper": null, "order": 107}, {"M": "Mz1", "seg1": "Mujer", "seg2": ["Estudios", "universitarios", "o m\u00e1s"], "cat": "S\u00ed", "prop": null, "lower": null, "upper": null, "order": 108}, {"M": "Mz1", "seg1": "Mujer", "seg2": ["Estudios", "universitarios", "o m\u00e1s"], "cat": "No", "prop": null, "lower": null, "upper": null, "order": 109}, {"M": "Mz1", "seg1": "Mujer", "seg2": ["Total"], "cat": "S\u00ed", "prop": null, "lower": null, "upper": null, "order": 110}, {"M": "Mz1", "seg1": "Mujer", "seg2": ["Total"], "cat": "No", "prop": null, "lower": null, "upper": null, "order": 111}, {"M": "Mz1", "seg1": "Total", "seg2": ["Hasta", "primaria"], "cat": "S\u00ed", "prop": null, "lower": null, "upper": null, "order": 112}, {"M": "Mz1", "seg1": "Total", "seg2": ["Hasta", "primaria"], "cat": "No", "prop": null, "lower": null, "upper": null, "order": 113}, {"M": "Mz1", "seg1": "Total", "seg2": ["Secundaria o", "FP grado sup"], "cat": "S\u00ed", "prop": null, "lower": null, "upper": null, "order": 114}, {"M": "Mz1", "seg1": "Total", "seg2": ["Secundaria o", "FP grado sup"], "cat": "No", "prop": null, "lower": null, "upper": null, "order": 115}, {"M": "Mz1", "seg1": "Total", "seg2": ["Estudios", "universitarios", "o m\u00e1s"], "cat": "S\u00ed", "prop": null, "lower": null, "upper": null, "order": 116}, {"M": "Mz1", "seg1": "Total", "seg2": ["Estudios", "universitarios", "o m\u00e1s"], "cat": "No", "prop": null, "lower": null, "upper": null, "order": 117}, {"M": "Mz1", "seg1": "Total", "seg2": ["Total"], "cat": "S\u00ed", "prop": null, "lower": null, "upper": null, "order": 118}, {"M": "Mz1", "seg1": "Total", "seg2": ["Total"], "cat": "No", "prop": null, "lower": null, "upper": null, "order": 119}, {"M": "Mz2", "seg1": "Hombre", "seg2": ["Hasta", "primaria"], "cat": "S\u00ed", "prop": null, "lower": null, "upper": null, "order": 120}, {"M": "Mz2", "seg1": "Hombre", "seg2": ["Hasta", "primaria"], "cat": "No", "prop": null, "lower": null, "upper": null, "order": 121}, {"M": "Mz2", "seg1": "Hombre", "seg2": ["Secundaria o", "FP grado sup"], "cat": "S\u00ed", "prop": null, "lower": null, "upper": null, "order": 122}, {"M": "Mz2", "seg1": "Hombre", "seg2": ["Secundaria o", "FP grado sup"], "cat": "No", "prop": null, "lower": null, "upper": null, "order": 123}, {"M": "Mz2", "seg1": "Hombre", "seg2": ["Estudios", "universitarios", "o m\u00e1s"], "cat": "S\u00ed", "prop": null, "lower": null, "upper": null, "order": 124}, {"M": "Mz2", "seg1": "Hombre", "seg2": ["Estudios", "universitarios", "o m\u00e1s"], "cat": "No", "prop": null, "lower": null, "upper": null, "order": 125}, {"M": "Mz2", "seg1": "Hombre", "seg2": ["Total"], "cat": "S\u00ed", "prop": null, "lower": null, "upper": null, "order": 126}, {"M": "Mz2", "seg1": "Hombre", "seg2": ["Total"], "cat": "No", "prop": null, "lower": null, "upper": null, "order": 127}, {"M": "Mz2", "seg1": "Mujer", "seg2": ["Hasta", "primaria"], "cat": "S\u00ed", "prop": null, "lower": null, "upper": null, "order": 128}, {"M": "Mz2", "seg1": "Mujer", "seg2": ["Hasta", "primaria"], "cat": "No", "prop": null, "lower": null, "upper": null, "order": 129}, {"M": "Mz2", "seg1": "Mujer", "seg2": ["Secundaria o", "FP grado sup"], "cat": "S\u00ed", "prop": null, "lower": null, "upper": null, "order": 130}, {"M": "Mz2", "seg1": "Mujer", "seg2": ["Secundaria o", "FP grado sup"], "cat": "No", "prop": null, "lower": null, "upper": null, "order": 131}, {"M": "Mz2", "seg1": "Mujer", "seg2": ["Estudios", "universitarios", "o m\u00e1s"], "cat": "S\u00ed", "prop": null, "lower": null, "upper": null, "order": 132}, {"M": "Mz2", "seg1": "Mujer", "seg2": ["Estudios", "universitarios", "o m\u00e1s"], "cat": "No", "prop": null, "lower": null, "upper": null, "order": 133}, {"M": "Mz2", "seg1": "Mujer", "seg2": ["Total"], "cat": "S\u00ed", "prop": null, "lower": null, "upper": null, "order": 134}, {"M": "Mz2", "seg1": "Mujer", "seg2": ["Total"], "cat": "No", "prop": null, "lower": null, "upper": null, "order": 135}, {"M": "Mz2", "seg1": "Total", "seg2": ["Hasta", "primaria"], "cat": "S\u00ed", "prop": null, "lower": null, "upper": null, "order": 136}, {"M": "Mz2", "seg1": "Total", "seg2": ["Hasta", "primaria"], "cat": "No", "prop": null, "lower": null, "upper": null, "order": 137}, {"M": "Mz2", "seg1": "Total", "seg2": ["Secundaria o", "FP grado sup"], "cat": "S\u00ed", "prop": null, "lower": null, "upper": null, "order": 138}, {"M": "Mz2", "seg1": "Total", "seg2": ["Secundaria o", "FP grado sup"], "cat": "No", "prop": null, "lower": null, "upper": null, "order": 139}, {"M": "Mz2", "seg1": "Total", "seg2": ["Estudios", "universitarios", "o m\u00e1s"], "cat": "S\u00ed", "prop": null, "lower": null, "upper": null, "order": 140}, {"M": "Mz2", "seg1": "Total", "seg2": ["Estudios", "universitarios", "o m\u00e1s"], "cat": "No", "prop": null, "lower": null, "upper": null, "order": 141}, {"M": "Mz2", "seg1": "Total", "seg2": ["Total"], "cat": "S\u00ed", "prop": null, "lower": null, "upper": null, "order": 142}, {"M": "Mz2", "seg1": "Total", "seg2": ["Total"], "cat": "No", "prop": null, "lower": null, "upper": null, "order": 143}]}}