{"config": {"view": {"continuousWidth": 300, "continuousHeight": 300}, "locale": {"number": {"decimal": ",", "thousands": ".", "grouping": [3], "currency": ["", "\u00a0\u20ac"]}}, "title": {"dx": 30, "dy": -15, "fontSize": 15}}, "vconcat": [{"facet": {"column": {"field": "seg", "header": {"labelFontSize": 15}, "sort": {"field": "order"}, "title": null, "type": "nominal"}, "row": {"field": "type", "header": {"labelFontSize": 15}, "sort": {"field": "order"}, "title": null, "type": "nominal"}}, "spec": {"layer": [{"mark": {"type": "rule"}, "encoding": {"y": {"aggregate": "mean", "field": "zero", "type": "quantitative"}}, "transform": [{"calculate": "0", "as": "zero"}]}, {"mark": {"type": "errorbar", "ticks": true}, "encoding": {"color": {"field": "type", "legend": null, "scale": {"range": ["DarkViolet", "DarkMagenta"]}, "sort": {"field": "order"}, "title": null, "type": "nominal"}, "tooltip": {"value": null}, "x": {"axis": {"labelAngle": 0, "labelFontSize": 11}, "field": "M", "sort": {"field": "order"}, "title": null, "type": "nominal"}, "y": {"axis": {"labelFontSize": 11}, "field": "lower", "title": null, "type": "quantitative"}, "y2": {"field": "upper"}}}, {"mark": {"type": "line", "point": {"size": 50}}, "encoding": {"color": {"field": "type", "legend": null, "scale": {"range": ["DarkViolet", "DarkMagenta"]}, "sort": {"field": "order"}, "title": null, "type": "nominal"}, "tooltip": [{"field": "prop", "format": ".2f", "title": "Estimaci\u00f3n", "type": "quantitative"}, {"field": "lower", "format": ".2f", "title": "L\u00edmite inferior", "type": "quantitative"}, {"field": "upper", "format": ".2f", "title": "L\u00edmite superior", "type": "quantitative"}], "x": {"axis": {"labelAngle": 0, "labelFontSize": 11}, "field": "M", "sort": {"field": "order"}, "title": null, "type": "nominal"}, "y": {"axis": {"labelFontSize": 11}, "field": "prop", "title": null, "type": "quantitative"}}, "name": "view_2016"}], "height": 175, "width": 175}, "resolve": {"axis": {"x": "independent", "y": "independent"}}, "transform": [{"filter": "datum.type == 'Absoluta (puntos porcentuales)'"}]}, {"facet": {"column": {"field": "seg", "header": {"labelFontSize": 15}, "sort": {"field": "order"}, "title": null, "type": "nominal"}, "row": {"field": "type", "header": {"labelFontSize": 15}, "sort": {"field": "order"}, "title": null, "type": "nominal"}}, "spec": {"layer": [{"mark": {"type": "rule"}, "encoding": {"y": {"aggregate": "mean", "field": "zero", "type": "quantitative"}}, "transform": [{"calculate": "0", "as": "zero"}]}, {"mark": {"type": "errorbar", "ticks": true}, "encoding": {"color": {"field": "type", "legend": null, "scale": {"range": ["DarkViolet", "DarkMagenta"]}, "sort": {"field": "order"}, "title": null, "type": "nominal"}, "tooltip": {"value": null}, "x": {"axis": {"labelAngle": 0, "labelFontSize": 11}, "field": "M", "sort": {"field": "order"}, "title": null, "type": "nominal"}, "y": {"axis": {"labelFontSize": 11}, "field": "lower", "title": null, "type": "quantitative"}, "y2": {"field": "upper"}}}, {"mark": {"type": "line", "point": {"size": 50}}, "encoding": {"color": {"field": "type", "legend": null, "scale": {"range": ["DarkViolet", "DarkMagenta"]}, "sort": {"field": "order"}, "title": null, "type": "nominal"}, "tooltip": [{"field": "prop", "format": ".2f", "title": "Estimaci\u00f3n", "type": "quantitative"}, {"field": "lower", "format": ".2f", "title": "L\u00edmite inferior", "type": "quantitative"}, {"field": "upper", "format": ".2f", "title": "L\u00edmite superior", "type": "quantitative"}], "x": {"axis": {"labelAngle": 0, "labelFontSize": 11}, "field": "M", "sort": {"field": "order"}, "title": null, "type": "nominal"}, "y": {"axis": {"labelFontSize": 11}, "field": "prop", "title": null, "type": "quantitative"}}, "name": "view_2017"}], "height": 175, "width": 175}, "resolve": {"axis": {"x": "independent", "y": "independent"}}, "transform": [{"filter": "datum.type == 'Relativa (%)'"}]}], "data": {"name": "data-62b6311c5697d4b8c5501a659e0650ee"}, "params": [{"name": "param_3483", "select": {"type": "interval", "encodings": ["x", "y"]}, "bind": "scales", "views": ["view_2016"]}, {"name": "param_3484", "select": {"type": "interval", "encodings": ["x", "y"]}, "bind": "scales", "views": ["view_2017"]}], "title": {"text": ["Brechas de g\u00e9nero de: Poblaci\u00f3n que tiene menos o mucha menos posibilidad de la que desea de hablar con alguien de sus problemas personales", "y familiares seg\u00fan grado de urbanizaci\u00f3n (puntos porcentuales / porcentajes e intervalos de confianza al 95%)"], "subtitle": "Fuente: Encuesta Sanitaria y Social de Andaluc\u00eda. C\u00f3digo de variable: P23_7_R"}, "transform": [{"filter": "indexof(datum.M, 'M') != -1"}], "$schema": "https://vega.github.io/schema/vega-lite/v5.14.1.json", "datasets": {"data-62b6311c5697d4b8c5501a659e0650ee": [{"type": "Absoluta (puntos porcentuales)", "M": "M2", "seg": "Urbano", "prop": 3.5872038668604516, "lower": 0.8048117261587011, "upper": 6.282009537090862, "order": 0}, {"type": "Absoluta (puntos porcentuales)", "M": "M2", "seg": "Intermedio", "prop": 0.5067007132995196, "lower": -3.1222825908405274, "upper": 4.312726435220079, "order": 1}, {"type": "Absoluta (puntos porcentuales)", "M": "M2", "seg": "Rural", "prop": 1.3832168507069156, "lower": -3.9573511821877205, "upper": 7.019338654370799, "order": 2}, {"type": "Absoluta (puntos porcentuales)", "M": "M2", "seg": "Total", "prop": 2.103337882553438, "lower": 0.05347410483371517, "upper": 4.085144395739124, "order": 3}, {"type": "Absoluta (puntos porcentuales)", "M": "M3", "seg": "Urbano", "prop": -0.4782355687854505, "lower": -2.9024455116475707, "upper": 1.82217658933969, "order": 4}, {"type": "Absoluta (puntos porcentuales)", "M": "M3", "seg": "Intermedio", "prop": -0.7175106189916964, "lower": -4.660270272426912, "upper": 2.306581641318259, "order": 5}, {"type": "Absoluta (puntos porcentuales)", "M": "M3", "seg": "Rural", "prop": -3.8951589000737377, "lower": -15.11575437539611, "upper": 2.9991641426730653, "order": 6}, {"type": "Absoluta (puntos porcentuales)", "M": "M3", "seg": "Total", "prop": -1.0219850600199503, "lower": -2.9817240324942675, "upper": 1.2001074604817636, "order": 7}, {"type": "Absoluta (puntos porcentuales)", "M": "M4", "seg": "Urbano", "prop": 2.4268023178257847, "lower": 0.007717759921166978, "upper": 5.140219350921139, "order": 8}, {"type": "Absoluta (puntos porcentuales)", "M": "M4", "seg": "Intermedio", "prop": 0.4395247770272448, "lower": -1.78167042768818, "upper": 2.7834423302016074, "order": 9}, {"type": "Absoluta (puntos porcentuales)", "M": "M4", "seg": "Rural", "prop": 0.3178813747687456, "lower": -8.394285762279937, "upper": 6.43653718376247, "order": 10}, {"type": "Absoluta (puntos porcentuales)", "M": "M4", "seg": "Total", "prop": 1.427939176956425, "lower": -0.4589371802992962, "upper": 3.209321142119717, "order": 11}, {"type": "Absoluta (puntos porcentuales)", "M": "Mz1", "seg": "Urbano", "prop": -0.18775195257505206, "lower": -3.5886535029329716, "upper": 3.278998549068304, "order": 12}, {"type": "Absoluta (puntos porcentuales)", "M": "Mz1", "seg": "Intermedio", "prop": 0.5294290353105496, "lower": -5.802030107383493, "upper": 7.782850619909569, "order": 13}, {"type": "Absoluta (puntos porcentuales)", "M": "Mz1", "seg": "Rural", "prop": null, "lower": null, "upper": null, "order": 14}, {"type": "Absoluta (puntos porcentuales)", "M": "Mz1", "seg": "Total", "prop": -0.015217448858217963, "lower": -2.9286878297649634, "upper": 3.187103990759476, "order": 15}, {"type": "Relativa (%)", "M": "M2", "seg": "Urbano", "prop": 92.47719722087753, "lower": 15.695271817022881, "upper": 226.8118789218617, "order": 16}, {"type": "Relativa (%)", "M": "M2", "seg": "Intermedio", "prop": 7.880384512041497, "lower": -40.281327303184675, "upper": 92.75957009630298, "order": 17}, {"type": "Relativa (%)", "M": "M2", "seg": "Rural", "prop": 23.51319122850874, "lower": -48.21923410029445, "upper": 238.52191120679538, "order": 18}, {"type": "Relativa (%)", "M": "M2", "seg": "Total", "prop": 40.962951437297235, "lower": -0.010218361289583418, "upper": 95.21487008137474, "order": 19}, {"type": "Relativa (%)", "M": "M3", "seg": "Urbano", "prop": -8.700515203388726, "lower": -41.14641896780915, "upper": 43.95037920762867, "order": 20}, {"type": "Relativa (%)", "M": "M3", "seg": "Intermedio", "prop": -11.49797211784287, "lower": -52.86882684692947, "upper": 57.19730200276274, "order": 21}, {"type": "Relativa (%)", "M": "M3", "seg": "Rural", "prop": -33.40577089549381, "lower": -78.88384610077904, "upper": 44.905313086818026, "order": 22}, {"type": "Relativa (%)", "M": "M3", "seg": "Total", "prop": -15.616756730511728, "lower": -37.54807533734398, "upper": 22.803835104537672, "order": 23}, {"type": "Relativa (%)", "M": "M4", "seg": "Urbano", "prop": 43.945106674513376, "lower": -1.5477085268700013, "upper": 121.30145071093806, "order": 24}, {"type": "Relativa (%)", "M": "M4", "seg": "Intermedio", "prop": 9.670725690476315, "lower": -32.69662350540465, "upper": 81.66151143136173, "order": 25}, {"type": "Relativa (%)", "M": "M4", "seg": "Rural", "prop": 4.348063095673675, "lower": -65.37910132556028, "upper": 206.336847862113, "order": 26}, {"type": "Relativa (%)", "M": "M4", "seg": "Total", "prop": 26.691471965321607, "lower": -7.820241384332075, "upper": 72.11041875127418, "order": 27}, {"type": "Relativa (%)", "M": "Mz1", "seg": "Urbano", "prop": -1.6303859623407124, "lower": -27.137828991685087, "upper": 34.56951419008906, "order": 28}, {"type": "Relativa (%)", "M": "Mz1", "seg": "Intermedio", "prop": 4.900967097245591, "lower": -46.410232266459, "upper": 104.03212649353213, "order": 29}, {"type": "Relativa (%)", "M": "Mz1", "seg": "Rural", "prop": null, "lower": null, "upper": null, "order": 30}, {"type": "Relativa (%)", "M": "Mz1", "seg": "Total", "prop": -0.13414401282134367, "lower": -22.992645546956943, "upper": 32.50790695411621, "order": 31}]}}